{"intention": [{"T": "ThemeRoot", "C": "Thing", "S": "America", "M": "Line Symbol Method"}], "positive_samples": [{"S": ["Departamento de Jalapa"], "T": ["Disaster"], "M": ["Line Symbol Method"], "C": ["http://sweetontology.net/phenAtmoWindMesoscale/DownslopeWindStorm"]}, {"S": ["Laborie"], "T": ["Ecosystem"], "M": ["Line Symbol Method"], "C": ["http://sweetontology.net/phenGeolVolcano/EruptionCloud"]}, {"S": ["Provincia de Peravia"], "T": ["ThemeRoot"], "M": ["Line Symbol Method"], "C": ["http://sweetontology.net/matrWater/GranularIce"]}, {"S": ["Roraima"], "T": ["Weather"], "M": ["Line Symbol Method"], "C": ["http://sweetontology.net/matrEquipment/RechargeWell"]}, {"S": ["Par\u00e1"], "T": ["Geology"], "M": ["Line Symbol Method"], "C": ["http://sweetontology.net/propConductivity/HydraulicConductivity"]}, {"S": ["La Pampa"], "T": ["ThemeRoot"], "M": ["Line Symbol Method"], "C": ["http://sweetontology.net/phenAtmoFog/GroundFog"]}, {"S": ["Yukon"], "T": ["Energy"], "M": ["Line Symbol Method"], "C": ["http://sweetontology.net/phenAtmoCloud/BannerCloud"]}, {"S": ["Esp\u00edrito Santo"], "T": ["Health"], "M": ["Line Symbol Method"], "C": ["http://sweetontology.net/propSpeed/Inertia"]}, {"S": ["Choiseul"], "T": ["Geology"], "M": ["Line Symbol Method"], "C": ["http://sweetontology.net/matrEquipment/PumpingWell"]}, {"S": ["Provincia de Pinar del R\u00edo"], "T": ["Energy"], "M": ["Line Symbol Method"], "C": ["http://sweetontology.net/phenAtmoWindMesoscale/Forano"]}, {"S": ["Departamento de Jalapa"], "T": ["Weather"], "M": ["Line Symbol Method"], "C": ["http://sweetontology.net/realmHydroBody/CheckDam"]}, {"S": ["Choiseul"], "T": ["Geology"], "M": ["Line Symbol Method"], "C": ["http://sweetontology.net/matrEquipment/PumpingWell"]}, {"S": ["Provincia de Pinar del R\u00edo"], "T": ["Energy"], "M": ["Line Symbol Method"], "C": ["http://sweetontology.net/phenAtmoWindMesoscale/Forano"]}, {"S": ["Provincia de Azua"], "T": ["Agriculture"], "M": ["Line Symbol Method"], "C": ["http://sweetontology.net/propSpaceThickness/Snowpack"]}, {"S": ["Roraima"], "T": ["Weather"], "M": ["Line Symbol Method"], "C": ["http://sweetontology.net/matrEquipment/RechargeWell"]}, {"S": ["Departamento de Concepci\u00f3n"], "T": ["Disaster"], "M": ["Line Symbol Method"], "C": ["http://sweetontology.net/stateTimeFrequency/Unusual"]}, {"S": ["Parish of Saint Paul"], "T": ["ThemeRoot"], "M": ["Line Symbol Method"], "C": ["http://sweetontology.net/propSpeed/Momentum"]}, {"S": ["Departamento de Boaco"], "T": ["Geology"], "M": ["Line Symbol Method"], "C": ["http://sweetontology.net/matrOrganicCompound/MethanoicAcid"]}, {"S": ["Esp\u00edrito Santo"], "T": ["Health"], "M": ["Line Symbol Method"], "C": ["http://sweetontology.net/propSpeed/Inertia"]}, {"S": ["Belize"], "T": ["Geology"], "M": ["Line Symbol Method"], "C": ["http://sweetontology.net/matrAnimal/Flatworm"]}, {"S": ["Carabobo"], "T": ["Energy"], "M": ["Line Symbol Method"], "C": ["http://sweetontology.net/matrPlant/TreeRing"]}, {"S": ["Ica"], "T": ["Health"], "M": ["Line Symbol Method"], "C": ["http://sweetontology.net/phenAtmoFog/FrontalFog"]}, {"S": ["Santiago del Estero"], "T": ["Agriculture"], "M": ["Line Symbol Method"], "C": ["http://sweetontology.net/phenAtmo/Sunlit"]}, {"S": ["Laborie"], "T": ["Ecosystem"], "M": ["Line Symbol Method"], "C": ["http://sweetontology.net/phenGeolVolcano/EruptionCloud"]}, {"S": ["Departamento de Chalatenango"], "T": ["Disaster"], "M": ["Line Symbol Method"], "C": ["http://sweetontology.net/matrOrganicCompound/Halon1211"]}, {"S": ["Provincia de Santiago"], "T": ["Climate"], "M": ["Line Symbol Method"], "C": ["http://sweetontology.net/matrMicrobiota/Diazotroph"]}, {"S": ["Junin"], "T": ["Water"], "M": ["Line Symbol Method"], "C": ["http://sweetontology.net/matrEquipment/Equipment"]}, {"S": ["Ecuador"], "T": ["Disaster"], "M": ["Line Symbol Method"], "C": ["http://sweetontology.net/matrAnimal/Invertebrate"]}, {"S": ["Roraima"], "T": ["Weather"], "M": ["Line Symbol Method"], "C": ["http://sweetontology.net/matrEquipment/RechargeWell"]}, {"S": ["Louisiana"], "T": ["Disaster"], "M": ["Line Symbol Method"], "C": ["http://sweetontology.net/matrRockIgneous/VolcanicNeck"]}], "negative_samples": [{"S": ["Redonda"], "T": ["Geology"], "M": ["Others"], "C": ["http://sweetontology.net/phenAtmoWindMesoscale/Leste"]}, {"S": ["Sucre"], "T": ["Agriculture"], "M": ["Area Method"], "C": ["http://sweetontology.net/matrAnimal/Invertebrate"]}, {"S": ["Departamento de San Marcos"], "T": ["Water"], "M": ["MapMethodRoot"], "C": ["http://sweetontology.net/propCapacity/HeatCapacity"]}, {"S": ["Departamento de Valle"], "T": ["ThemeRoot"], "M": ["No Method"], "C": ["http://sweetontology.net/matrElement/Boron"]}, {"S": ["Yaracuy"], "T": ["Climate"], "M": ["Others"], "C": ["http://sweetontology.net/phenWave/Wave"]}, {"S": ["Saint George"], "T": ["Water"], "M": ["Choloplethic Method"], "C": ["http://sweetontology.net/propSpaceThickness/SWE"]}, {"S": ["Monagas"], "T": ["Water"], "M": ["No Method"], "C": ["http://sweetontology.net/matrAnimal/Millipede"]}, {"S": ["Departamento del Meta"], "T": ["ThemeRoot"], "M": ["No Method"], "C": ["http://sweetontology.net/matrWater/Sewage"]}, {"S": ["Distrikt Sipaliwini"], "T": ["Weather"], "M": ["MapMethodRoot"], "C": ["http://sweetontology.net/matrOrganicCompound/Alkene"]}, {"S": ["Ayacucho"], "T": ["Weather"], "M": ["Others"], "C": ["http://sweetontology.net/realmLandProtected/MarineProtectedArea"]}, {"S": ["Provincia de Camag\u00fcey"], "T": ["Water"], "M": ["Others"], "C": ["http://sweetontology.net/phenCycle/MilankovitchCycle"]}, {"S": ["Rio Grande do Sul"], "T": ["ThemeRoot"], "M": ["Point Symbol Method"], "C": ["http://sweetontology.net/matr/Air"]}, {"S": ["Mexico City"], "T": ["Biodiversity"], "M": ["Choloplethic Method"], "C": ["http://sweetontology.net/realmLandProtected/StateForest"]}, {"S": ["Redonda"], "T": ["Geology"], "M": ["Others"], "C": ["http://sweetontology.net/phenAtmoWindMesoscale/Leste"]}, {"S": ["Provincia de San Jos\u00e9"], "T": ["Agriculture"], "M": ["Quality Base Method"], "C": ["http://sweetontology.net/phenAtmoWindMesoscale/NorthFoehn"]}, {"S": ["San Salvador District"], "T": ["Ecosystem"], "M": ["Area Method"], "C": ["http://sweetontology.net/propSpeed/IonVelocity"]}, {"S": ["Mayaguana District"], "T": ["Energy"], "M": ["MapMethodRoot"], "C": ["http://sweetontology.net/matrOrganicCompound/Halon1301"]}, {"S": ["Rio Grande do Sul"], "T": ["ThemeRoot"], "M": ["Point Symbol Method"], "C": ["http://sweetontology.net/matr/Air"]}, {"S": ["Aguascalientes"], "T": ["Health"], "M": ["Point Symbol Method"], "C": ["http://sweetontology.net/matrInstrument/Microscope"]}, {"S": ["El Salvador"], "T": ["Ecosystem"], "M": ["MapMethodRoot"], "C": ["http://sweetontology.net/reprTimeSeason/ColdestMonth"]}, {"S": ["Redonda"], "T": ["Geology"], "M": ["Others"], "C": ["http://sweetontology.net/phenAtmoWindMesoscale/Leste"]}, {"S": ["San Luis"], "T": ["Water"], "M": ["MapMethodRoot"], "C": ["http://sweetontology.net/propCapacity/HeatCapacity"]}, {"S": ["D\u00e9partement du Nord-Est"], "T": ["Ecosystem"], "M": ["Quality Base Method"], "C": ["http://sweetontology.net/matrCompound/ChlorineDioxide"]}, {"S": ["Ancash"], "T": ["Health"], "M": ["Quality Base Method"], "C": ["http://sweetontology.net/matrWater/IceParticle"]}, {"S": ["Catamarca"], "T": ["Water"], "M": ["Area Method"], "C": ["http://sweetontology.net/matrBiomass/Detritus"]}, {"S": ["Departamento de Cochabamba"], "T": ["Ecosystem"], "M": ["MapMethodRoot"], "C": ["http://sweetontology.net/matrAnimal/Arthropod"]}, {"S": ["Parish of Saint John"], "T": ["Geology"], "M": ["Area Method"], "C": ["http://sweetontology.net/phenWave/SurfaceWave"]}, {"S": ["Princes Town"], "T": ["Water"], "M": ["No Method"], "C": ["http://sweetontology.net/matrRockIgneous/Xenocryst"]}, {"S": ["Provincia del Azuay"], "T": ["Disaster"], "M": ["Quality Base Method"], "C": ["http://sweetontology.net/phenAtmoCloud/Cirrus"]}, {"S": ["Distrikt Coronie"], "T": ["Health"], "M": ["Quality Base Method"], "C": ["http://sweetontology.net/matrAerosol/CondensationNuclei"]}]}