{"intention": [{"T": "Geology", "C": "http://sweetontology.net/matrRock/Rock", "S": "America", "M": "Point Symbol Method"}, {"T": "Weather", "C": "http://sweetontology.net/propTemperature/Temperature", "S": "United States", "M": "MapMethodRoot"}], "positive_samples": [{"S": ["Provincia de Bocas del Toro"], "T": ["Geology"], "M": ["Point Symbol Method"], "C": ["http://sweetontology.net/matrRockIgneous/Lava"]}, {"S": ["Corrientes"], "T": ["Geology"], "M": ["Point Symbol Method"], "C": ["http://sweetontology.net/matrRock/Meteor"]}, {"S": ["New Mexico"], "T": ["Geology"], "M": ["Point Symbol Method"], "C": ["http://sweetontology.net/matrRockIgneous/Tephra"]}, {"S": ["Colorado"], "T": ["Geology"], "M": ["Point Symbol Method"], "C": ["http://sweetontology.net/matrRockIgneous/Kimberlite"]}, {"S": ["Connecticut"], "T": ["Geology"], "M": ["Point Symbol Method"], "C": ["http://sweetontology.net/matrRockIgneous/TuffRing"]}, {"S": ["Tabasco"], "T": ["Geology"], "M": ["Point Symbol Method"], "C": ["http://sweetontology.net/matrRockIgneous/PillowLava"]}, {"S": ["Tabasco"], "T": ["Geology"], "M": ["Point Symbol Method"], "C": ["http://sweetontology.net/matrRockIgneous/Xenolith"]}, {"S": ["Provincia de Santa Elena"], "T": ["Geology"], "M": ["Point Symbol Method"], "C": ["http://sweetontology.net/matrRockIgneous/Mafic"]}, {"S": ["Provincia de Bocas del Toro"], "T": ["Geology"], "M": ["Point Symbol Method"], "C": ["http://sweetontology.net/matrRockIgneous/Lava"]}, {"S": ["Provincia de Ciego de \u00c1vila"], "T": ["Geology"], "M": ["Point Symbol Method"], "C": ["http://sweetontology.net/matrRockIgneous/AnorogenicIgneousRock"]}, {"S": ["Coquimbo Region"], "T": ["Geology"], "M": ["Point Symbol Method"], "C": ["http://sweetontology.net/matrRockIgneous/AnorogenicIgneousRock"]}, {"S": ["Provincia Mar\u00eda Trinidad S\u00e1nchez"], "T": ["Geology"], "M": ["Point Symbol Method"], "C": ["http://sweetontology.net/matrRockIgneous/Trachybasalt"]}, {"S": ["California"], "T": ["Weather"], "M": ["Quality Base Method"], "C": ["http://sweetontology.net/propTemperature/DewPoint"]}, {"S": ["Illinois"], "T": ["Weather"], "M": ["Line Symbol Method"], "C": ["http://sweetontology.net/propTemperature/TriplePoint"]}, {"S": ["Texas"], "T": ["Weather"], "M": ["No Method"], "C": ["http://sweetontology.net/propTemperature/BoilingPoint"]}, {"S": ["North Dakota"], "T": ["Weather"], "M": ["Choloplethic Method"], "C": ["http://sweetontology.net/propTemperature/WetBulbTemperature"]}, {"S": ["New Jersey"], "T": ["Weather"], "M": ["Point Symbol Method"], "C": ["http://sweetontology.net/propTemperature/NeutralTemperature"]}, {"S": ["Texas"], "T": ["Weather"], "M": ["No Method"], "C": ["http://sweetontology.net/propTemperature/BoilingPoint"]}, {"S": ["North Dakota"], "T": ["Weather"], "M": ["Point Symbol Method"], "C": ["http://sweetontology.net/propTemperature/DewPointTemperature"]}, {"S": ["Hawaii"], "T": ["Weather"], "M": ["Area Method"], "C": ["http://sweetontology.net/propTemperature/WindChill"]}, {"S": ["New York"], "T": ["Weather"], "M": ["Point Symbol Method"], "C": ["http://sweetontology.net/propTemperature/ElectronTemperature"]}, {"S": ["Arkansas"], "T": ["Weather"], "M": ["Area Method"], "C": ["http://sweetontology.net/propTemperature/PseudoEquivalentTemperature"]}, {"S": ["South Carolina"], "T": ["Weather"], "M": ["MapMethodRoot"], "C": ["http://sweetontology.net/propTemperature/PotentialTemperature"]}, {"S": ["North Dakota"], "T": ["Weather"], "M": ["Point Symbol Method"], "C": ["http://sweetontology.net/propTemperature/DewPointTemperature"]}, {"S": ["Washington"], "T": ["Weather"], "M": ["Line Symbol Method"], "C": ["http://sweetontology.net/propTemperature/DewPoint"]}], "negative_samples": [{"S": ["Coahuila"], "T": ["Weather"], "M": ["MapMethodRoot"], "C": ["http://sweetontology.net/propTemperature/Temperature"]}, {"S": ["Saint Mary Cayon"], "T": ["Geology"], "M": ["Point Symbol Method"], "C": ["http://sweetontology.net/matrSediment/Mud"]}, {"S": ["Rio Grande do Sul"], "T": ["Health"], "M": ["Point Symbol Method"], "C": ["http://sweetontology.net/matrElement/Lithium"]}, {"S": ["St Kitts and Nevis"], "T": ["Weather"], "M": ["MapMethodRoot"], "C": ["http://sweetontology.net/propTemperature/AntennaTemperature"]}, {"S": ["Departamento de Intibuc\u00e1"], "T": ["Geology"], "M": ["Point Symbol Method"], "C": ["http://sweetontology.net/matr/Air"]}, {"S": ["Maine"], "T": ["Agriculture"], "M": ["Others"], "C": ["http://sweetontology.net/matrMicrobiota/MicrobiotaTaxonomy"]}, {"S": ["Departamento de Potos\u00ed"], "T": ["Geology"], "M": ["Point Symbol Method"], "C": ["http://sweetontology.net/matrSediment/Sediment"]}, {"S": ["Sonora"], "T": ["Water"], "M": ["Point Symbol Method"], "C": ["http://sweetontology.net/matrFacility/Base"]}, {"S": ["Provincia de Guanacaste"], "T": ["Geology"], "M": ["Point Symbol Method"], "C": ["http://sweetontology.net/matr/Air"]}, {"S": ["Mississippi"], "T": ["Weather"], "M": ["Point Symbol Method"], "C": ["http://sweetontology.net/propTemperatureGradient/AutoConvectiveLapseRate"]}, {"S": ["Utah"], "T": ["Weather"], "M": ["Others"], "C": ["http://sweetontology.net/propEnergyFlux/ThermalFlux"]}, {"S": ["Aguascalientes"], "T": ["Disaster"], "M": ["MapMethodRoot"], "C": ["http://sweetontology.net/matrIsotope/He3"]}, {"S": ["Oklahoma"], "T": ["Weather"], "M": ["Area Method"], "C": ["http://sweetontology.net/propCapacity/VolumetricHeatCapacity"]}, {"S": ["Yucat\u00e1n"], "T": ["Weather"], "M": ["Area Method"], "C": ["http://sweetontology.net/propTemperature/Temperature"]}, {"S": ["United States"], "T": ["Weather"], "M": ["Line Symbol Method"], "C": ["http://sweetontology.net/matrElement/TraceMetal"]}, {"S": ["Coahuila"], "T": ["Weather"], "M": ["MapMethodRoot"], "C": ["http://sweetontology.net/propTemperature/Temperature"]}, {"S": ["Utah"], "T": ["Weather"], "M": ["Others"], "C": ["http://sweetontology.net/propEnergyFlux/ThermalFlux"]}, {"S": ["Provincia de Pichincha"], "T": ["Energy"], "M": ["No Method"], "C": ["http://sweetontology.net/realmLandProtected/WildlifeRefuge"]}, {"S": ["United States"], "T": ["Weather"], "M": ["Area Method"], "C": ["http://sweetontology.net/matrOrganicCompound/Carbonyl"]}, {"S": ["Haiti"], "T": ["Weather"], "M": ["Area Method"], "C": ["http://sweetontology.net/propTemperature/NeutralTemperature"]}, {"S": ["Massachusetts"], "T": ["Weather"], "M": ["Quality Base Method"], "C": ["http://sweetontology.net/propCapacity/ThermalExpansionCoefficient"]}, {"S": ["Provincia de Pichincha"], "T": ["Energy"], "M": ["No Method"], "C": ["http://sweetontology.net/realmLandProtected/WildlifeRefuge"]}, {"S": ["Coahuila"], "T": ["Disaster"], "M": ["Point Symbol Method"], "C": ["http://sweetontology.net/propCapacity/LinearThermalExpansion"]}, {"S": ["New York"], "T": ["Weather"], "M": ["No Method"], "C": ["http://sweetontology.net/propQuantity/ThermodynamicQuantity"]}, {"S": ["Provincia de Cartago"], "T": ["Geology"], "M": ["Point Symbol Method"], "C": ["http://sweetontology.net/matrSediment/Cobble"]}]}